{"AUD":{"broj_tecajnice":"135","datum_primjene":"2020-07-15","drzava":"Australija","drzava_iso":"AUS","sifra_valute":"036","valuta":"AUD","jedinica":1,"kupovni_tecaj":"4,596262","srednji_tecaj":"4,610092","prodajni_tecaj":"4,623922","name":"Australia Dollar"},"CAD":{"broj_tecajnice":"135","datum_primjene":"2020-07-15","drzava":"Kanada","drzava_iso":"CAN","sifra_valute":"124","valuta":"CAD","jedinica":1,"kupovni_tecaj":"4,853077","srednji_tecaj":"4,867680","prodajni_tecaj":"4,882283","name":"Canada Dollar"},"CZK":{"broj_tecajnice":"135","datum_primjene":"2020-07-15","drzava":"\u010ce\u0161ka","drzava_iso":"CZE","sifra_valute":"203","valuta":"CZK","jedinica":1,"kupovni_tecaj":"0,281631","srednji_tecaj":"0,282478","prodajni_tecaj":"0,283325","name":"Czech Republic Koruna"},"DKK":{"broj_tecajnice":"135","datum_primjene":"2020-07-15","drzava":"Danska","drzava_iso":"DNK","sifra_valute":"208","valuta":"DKK","jedinica":1,"kupovni_tecaj":"1,009344","srednji_tecaj":"1,012381","prodajni_tecaj":"1,015418","name":"Denmark Krone"},"HUF":{"broj_tecajnice":"135","datum_primjene":"2020-07-15","drzava":"Ma\u0111arska","drzava_iso":"HUN","sifra_valute":"348","valuta":"HUF","jedinica":100,"kupovni_tecaj":"2,114922","srednji_tecaj":"2,121286","prodajni_tecaj":"2,127650","name":"Hungary Forint"},"JPY":{"broj_tecajnice":"135","datum_primjene":"2020-07-15","drzava":"Japan","drzava_iso":"JPN","sifra_valute":"392","valuta":"JPY","jedinica":100,"kupovni_tecaj":"6,162278","srednji_tecaj":"6,180820","prodajni_tecaj":"6,199362","name":"Japan Yen"},"NOK":{"broj_tecajnice":"135","datum_primjene":"2020-07-15","drzava":"Norve\u0161ka","drzava_iso":"NOR","sifra_valute":"578","valuta":"NOK","jedinica":1,"kupovni_tecaj":"0,700714","srednji_tecaj":"0,702822","prodajni_tecaj":"0,704930","name":"Norway Krone"},"SEK":{"broj_tecajnice":"135","datum_primjene":"2020-07-15","drzava":"\u0160vedska","drzava_iso":"SWE","sifra_valute":"752","valuta":"SEK","jedinica":1,"kupovni_tecaj":"0,722312","srednji_tecaj":"0,724485","prodajni_tecaj":"0,726658","name":"Sweden Krona"},"CHF":{"broj_tecajnice":"135","datum_primjene":"2020-07-15","drzava":"\u0160vicarska","drzava_iso":"CHE","sifra_valute":"756","valuta":"CHF","jedinica":1,"kupovni_tecaj":"7,037325","srednji_tecaj":"7,058501","prodajni_tecaj":"7,079677","name":"Switzerland Franc"},"GBP":{"broj_tecajnice":"135","datum_primjene":"2020-07-15","drzava":"Velika Britanija","drzava_iso":"GBR","sifra_valute":"826","valuta":"GBP","jedinica":1,"kupovni_tecaj":"8,280667","srednji_tecaj":"8,305584","prodajni_tecaj":"8,330501","name":"United Kingdom Pound"},"USD":{"broj_tecajnice":"135","datum_primjene":"2020-07-15","drzava":"SAD","drzava_iso":"USA","sifra_valute":"840","valuta":"USD","jedinica":1,"kupovni_tecaj":"6,613600","srednji_tecaj":"6,633500","prodajni_tecaj":"6,653401","name":"United States Dollar"},"BAM":{"broj_tecajnice":"135","datum_primjene":"2020-07-15","drzava":"Bosna i Hercegovina","drzava_iso":"BIH","sifra_valute":"977","valuta":"BAM","jedinica":1,"kupovni_tecaj":"3,841361","srednji_tecaj":"3,852920","prodajni_tecaj":"3,864479","name":"BA Convertible Marka"},"EUR":{"broj_tecajnice":"135","datum_primjene":"2020-07-15","drzava":"EMU","drzava_iso":"EMU","sifra_valute":"978","valuta":"EUR","jedinica":1,"kupovni_tecaj":"7,513049","srednji_tecaj":"7,535656","prodajni_tecaj":"7,558263","name":"Euro Member Countries"},"PLN":{"broj_tecajnice":"135","datum_primjene":"2020-07-15","drzava":"Poljska","drzava_iso":"POL","sifra_valute":"985","valuta":"PLN","jedinica":1,"kupovni_tecaj":"1,674964","srednji_tecaj":"1,680004","prodajni_tecaj":"1,685044","name":"Poland Zloty"}}