{"AUD":{"broj_tecajnice":"129","datum_primjene":"2020-07-07","drzava":"Australija","drzava_iso":"AUS","sifra_valute":"036","valuta":"AUD","jedinica":1,"kupovni_tecaj":"4,642655","srednji_tecaj":"4,656625","prodajni_tecaj":"4,670595","name":"Australia Dollar"},"CAD":{"broj_tecajnice":"129","datum_primjene":"2020-07-07","drzava":"Kanada","drzava_iso":"CAN","sifra_valute":"124","valuta":"CAD","jedinica":1,"kupovni_tecaj":"4,919680","srednji_tecaj":"4,934483","prodajni_tecaj":"4,949286","name":"Canada Dollar"},"CZK":{"broj_tecajnice":"129","datum_primjene":"2020-07-07","drzava":"\u010ce\u0161ka","drzava_iso":"CZE","sifra_valute":"203","valuta":"CZK","jedinica":1,"kupovni_tecaj":"0,282123","srednji_tecaj":"0,282972","prodajni_tecaj":"0,283821","name":"Czech Republic Koruna"},"DKK":{"broj_tecajnice":"129","datum_primjene":"2020-07-07","drzava":"Danska","drzava_iso":"DNK","sifra_valute":"208","valuta":"DKK","jedinica":1,"kupovni_tecaj":"1,010253","srednji_tecaj":"1,013293","prodajni_tecaj":"1,016333","name":"Denmark Krone"},"HUF":{"broj_tecajnice":"129","datum_primjene":"2020-07-07","drzava":"Ma\u0111arska","drzava_iso":"HUN","sifra_valute":"348","valuta":"HUF","jedinica":100,"kupovni_tecaj":"2,134581","srednji_tecaj":"2,141004","prodajni_tecaj":"2,147427","name":"Hungary Forint"},"JPY":{"broj_tecajnice":"129","datum_primjene":"2020-07-07","drzava":"Japan","drzava_iso":"JPN","sifra_valute":"392","valuta":"JPY","jedinica":100,"kupovni_tecaj":"6,198617","srednji_tecaj":"6,217269","prodajni_tecaj":"6,235921","name":"Japan Yen"},"NOK":{"broj_tecajnice":"129","datum_primjene":"2020-07-07","drzava":"Norve\u0161ka","drzava_iso":"NOR","sifra_valute":"578","valuta":"NOK","jedinica":1,"kupovni_tecaj":"0,708280","srednji_tecaj":"0,710411","prodajni_tecaj":"0,712542","name":"Norway Krone"},"SEK":{"broj_tecajnice":"129","datum_primjene":"2020-07-07","drzava":"\u0160vedska","drzava_iso":"SWE","sifra_valute":"752","valuta":"SEK","jedinica":1,"kupovni_tecaj":"0,717700","srednji_tecaj":"0,719860","prodajni_tecaj":"0,722020","name":"Sweden Krona"},"CHF":{"broj_tecajnice":"129","datum_primjene":"2020-07-07","drzava":"\u0160vicarska","drzava_iso":"CHE","sifra_valute":"756","valuta":"CHF","jedinica":1,"kupovni_tecaj":"7,076144","srednji_tecaj":"7,097436","prodajni_tecaj":"7,118728","name":"Switzerland Franc"},"GBP":{"broj_tecajnice":"129","datum_primjene":"2020-07-07","drzava":"Velika Britanija","drzava_iso":"GBR","sifra_valute":"826","valuta":"GBP","jedinica":1,"kupovni_tecaj":"8,331601","srednji_tecaj":"8,356671","prodajni_tecaj":"8,381741","name":"United Kingdom Pound"},"USD":{"broj_tecajnice":"129","datum_primjene":"2020-07-07","drzava":"SAD","drzava_iso":"USA","sifra_valute":"840","valuta":"USD","jedinica":1,"kupovni_tecaj":"6,665724","srednji_tecaj":"6,685781","prodajni_tecaj":"6,705838","name":"United States Dollar"},"BAM":{"broj_tecajnice":"129","datum_primjene":"2020-07-07","drzava":"Bosna i Hercegovina","drzava_iso":"BIH","sifra_valute":"977","valuta":"BAM","jedinica":1,"kupovni_tecaj":"3,848802","srednji_tecaj":"3,860383","prodajni_tecaj":"3,871964","name":"BA Convertible Marka"},"EUR":{"broj_tecajnice":"129","datum_primjene":"2020-07-07","drzava":"EMU","drzava_iso":"EMU","sifra_valute":"978","valuta":"EUR","jedinica":1,"kupovni_tecaj":"7,527601","srednji_tecaj":"7,550252","prodajni_tecaj":"7,572903","name":"Euro Member Countries"},"PLN":{"broj_tecajnice":"129","datum_primjene":"2020-07-07","drzava":"Poljska","drzava_iso":"POL","sifra_valute":"985","valuta":"PLN","jedinica":1,"kupovni_tecaj":"1,683500","srednji_tecaj":"1,688566","prodajni_tecaj":"1,693632","name":"Poland Zloty"}}