{"AUD":{"broj_tecajnice":"154","datum_primjene":"2020-08-12","drzava":"Australija","drzava_iso":"AUS","sifra_valute":"036","valuta":"AUD","jedinica":1,"kupovni_tecaj":"4,532283","srednji_tecaj":"4,545921","prodajni_tecaj":"4,559559","name":"Australia Dollar"},"CAD":{"broj_tecajnice":"154","datum_primjene":"2020-08-12","drzava":"Kanada","drzava_iso":"CAN","sifra_valute":"124","valuta":"CAD","jedinica":1,"kupovni_tecaj":"4,750131","srednji_tecaj":"4,764424","prodajni_tecaj":"4,778717","name":"Canada Dollar"},"CZK":{"broj_tecajnice":"154","datum_primjene":"2020-08-12","drzava":"\u010ce\u0161ka","drzava_iso":"CZE","sifra_valute":"203","valuta":"CZK","jedinica":1,"kupovni_tecaj":"0,284257","srednji_tecaj":"0,285112","prodajni_tecaj":"0,285967","name":"Czech Republic Koruna"},"DKK":{"broj_tecajnice":"154","datum_primjene":"2020-08-12","drzava":"Danska","drzava_iso":"DNK","sifra_valute":"208","valuta":"DKK","jedinica":1,"kupovni_tecaj":"0,999228","srednji_tecaj":"1,002235","prodajni_tecaj":"1,005242","name":"Denmark Krone"},"HUF":{"broj_tecajnice":"154","datum_primjene":"2020-08-12","drzava":"Ma\u0111arska","drzava_iso":"HUN","sifra_valute":"348","valuta":"HUF","jedinica":100,"kupovni_tecaj":"2,157848","srednji_tecaj":"2,164341","prodajni_tecaj":"2,170834","name":"Hungary Forint"},"JPY":{"broj_tecajnice":"154","datum_primjene":"2020-08-12","drzava":"Japan","drzava_iso":"JPN","sifra_valute":"392","valuta":"JPY","jedinica":100,"kupovni_tecaj":"5,952291","srednji_tecaj":"5,970202","prodajni_tecaj":"5,988113","name":"Japan Yen"},"NOK":{"broj_tecajnice":"154","datum_primjene":"2020-08-12","drzava":"Norve\u0161ka","drzava_iso":"NOR","sifra_valute":"578","valuta":"NOK","jedinica":1,"kupovni_tecaj":"0,703647","srednji_tecaj":"0,705764","prodajni_tecaj":"0,707881","name":"Norway Krone"},"SEK":{"broj_tecajnice":"154","datum_primjene":"2020-08-12","drzava":"\u0160vedska","drzava_iso":"SWE","sifra_valute":"752","valuta":"SEK","jedinica":1,"kupovni_tecaj":"0,723809","srednji_tecaj":"0,725987","prodajni_tecaj":"0,728165","name":"Sweden Krona"},"CHF":{"broj_tecajnice":"154","datum_primjene":"2020-08-12","drzava":"\u0160vicarska","drzava_iso":"CHE","sifra_valute":"756","valuta":"CHF","jedinica":1,"kupovni_tecaj":"6,912731","srednji_tecaj":"6,933532","prodajni_tecaj":"6,954333","name":"Switzerland Franc"},"GBP":{"broj_tecajnice":"154","datum_primjene":"2020-08-12","drzava":"Velika Britanija","drzava_iso":"GBR","sifra_valute":"826","valuta":"GBP","jedinica":1,"kupovni_tecaj":"8,269313","srednji_tecaj":"8,294196","prodajni_tecaj":"8,319079","name":"United Kingdom Pound"},"USD":{"broj_tecajnice":"154","datum_primjene":"2020-08-12","drzava":"SAD","drzava_iso":"USA","sifra_valute":"840","valuta":"USD","jedinica":1,"kupovni_tecaj":"6,313358","srednji_tecaj":"6,332355","prodajni_tecaj":"6,351352","name":"United States Dollar"},"BAM":{"broj_tecajnice":"154","datum_primjene":"2020-08-12","drzava":"Bosna i Hercegovina","drzava_iso":"BIH","sifra_valute":"977","valuta":"BAM","jedinica":1,"kupovni_tecaj":"3,804807","srednji_tecaj":"3,816256","prodajni_tecaj":"3,827705","name":"BA Convertible Marka"},"EUR":{"broj_tecajnice":"154","datum_primjene":"2020-08-12","drzava":"EMU","drzava_iso":"EMU","sifra_valute":"978","valuta":"EUR","jedinica":1,"kupovni_tecaj":"7,441555","srednji_tecaj":"7,463947","prodajni_tecaj":"7,486339","name":"Euro Member Countries"},"PLN":{"broj_tecajnice":"154","datum_primjene":"2020-08-12","drzava":"Poljska","drzava_iso":"POL","sifra_valute":"985","valuta":"PLN","jedinica":1,"kupovni_tecaj":"1,690686","srednji_tecaj":"1,695773","prodajni_tecaj":"1,700860","name":"Poland Zloty"}}