{"AUD":{"broj_tecajnice":"164","datum_primjene":"2022-08-29","drzava":"Australija","drzava_iso":"AUS","sifra_valute":"036","valuta":"AUD","jedinica":1,"kupovni_tecaj":"5,227082","srednji_tecaj":"5,242810","prodajni_tecaj":"5,258538","name":"Australia Dollar"},"CAD":{"broj_tecajnice":"164","datum_primjene":"2022-08-29","drzava":"Kanada","drzava_iso":"CAN","sifra_valute":"124","valuta":"CAD","jedinica":1,"kupovni_tecaj":"5,789102","srednji_tecaj":"5,806522","prodajni_tecaj":"5,823942","name":"Canada Dollar"},"CZK":{"broj_tecajnice":"164","datum_primjene":"2022-08-29","drzava":"\u010ce\u0161ka","drzava_iso":"CZE","sifra_valute":"203","valuta":"CZK","jedinica":1,"kupovni_tecaj":"0,303816","srednji_tecaj":"0,304730","prodajni_tecaj":"0,305644","name":"Czech Republic Koruna"},"DKK":{"broj_tecajnice":"164","datum_primjene":"2022-08-29","drzava":"Danska","drzava_iso":"DNK","sifra_valute":"208","valuta":"DKK","jedinica":1,"kupovni_tecaj":"1,006946","srednji_tecaj":"1,009976","prodajni_tecaj":"1,013006","name":"Denmark Krone"},"HUF":{"broj_tecajnice":"164","datum_primjene":"2022-08-29","drzava":"Ma\u0111arska","drzava_iso":"HUN","sifra_valute":"348","valuta":"HUF","jedinica":100,"kupovni_tecaj":"1,829307","srednji_tecaj":"1,834811","prodajni_tecaj":"1,840315","name":"Hungary Forint"},"JPY":{"broj_tecajnice":"164","datum_primjene":"2022-08-29","drzava":"Japan","drzava_iso":"JPN","sifra_valute":"392","valuta":"JPY","jedinica":100,"kupovni_tecaj":"5,469882","srednji_tecaj":"5,486341","prodajni_tecaj":"5,502800","name":"Japan Yen"},"NOK":{"broj_tecajnice":"164","datum_primjene":"2022-08-29","drzava":"Norve\u0161ka","drzava_iso":"NOR","sifra_valute":"578","valuta":"NOK","jedinica":1,"kupovni_tecaj":"0,775385","srednji_tecaj":"0,777718","prodajni_tecaj":"0,780051","name":"Norway Krone"},"SEK":{"broj_tecajnice":"164","datum_primjene":"2022-08-29","drzava":"\u0160vedska","drzava_iso":"SWE","sifra_valute":"752","valuta":"SEK","jedinica":1,"kupovni_tecaj":"0,707893","srednji_tecaj":"0,710023","prodajni_tecaj":"0,712153","name":"Sweden Krona"},"CHF":{"broj_tecajnice":"164","datum_primjene":"2022-08-29","drzava":"\u0160vicarska","drzava_iso":"CHE","sifra_valute":"756","valuta":"CHF","jedinica":1,"kupovni_tecaj":"7,769048","srednji_tecaj":"7,792425","prodajni_tecaj":"7,815802","name":"Switzerland Franc"},"GBP":{"broj_tecajnice":"164","datum_primjene":"2022-08-29","drzava":"Velika Britanija","drzava_iso":"GBR","sifra_valute":"826","valuta":"GBP","jedinica":1,"kupovni_tecaj":"8,858957","srednji_tecaj":"8,885614","prodajni_tecaj":"8,912271","name":"United Kingdom Pound"},"USD":{"broj_tecajnice":"164","datum_primjene":"2022-08-29","drzava":"SAD","drzava_iso":"USA","sifra_valute":"840","valuta":"USD","jedinica":1,"kupovni_tecaj":"7,487116","srednji_tecaj":"7,509645","prodajni_tecaj":"7,532174","name":"United States Dollar"},"BAM":{"broj_tecajnice":"164","datum_primjene":"2022-08-29","drzava":"Bosna i Hercegovina","drzava_iso":"BIH","sifra_valute":"977","valuta":"BAM","jedinica":1,"kupovni_tecaj":"3,829250","srednji_tecaj":"3,840772","prodajni_tecaj":"3,852294","name":"BA Convertible Marka"},"EUR":{"broj_tecajnice":"164","datum_primjene":"2022-08-29","drzava":"EMU","drzava_iso":"EMU","sifra_valute":"978","valuta":"EUR","jedinica":1,"kupovni_tecaj":"7,489362","srednji_tecaj":"7,511898","prodajni_tecaj":"7,534434","name":"Euro Member Countries"},"PLN":{"broj_tecajnice":"164","datum_primjene":"2022-08-29","drzava":"Poljska","drzava_iso":"POL","sifra_valute":"985","valuta":"PLN","jedinica":1,"kupovni_tecaj":"1,577206","srednji_tecaj":"1,581952","prodajni_tecaj":"1,586698","name":"Poland Zloty"}}